sequence_builder/__init__.py
sequence_builder-0.0.2.dist-info/LICENSE.txt
sequence_builder-0.0.2.dist-info/METADATA
sequence_builder-0.0.2.dist-info/WHEEL
sequence_builder-0.0.2.dist-info/top_level.txt
sequence_builder-0.0.2.dist-info/RECORD
