Metadata-Version: 2.1
Name: sequence-builder
Version: 0.0.2
Summary: Building sequences from time-series data
Home-page: https://github.com/DoraSz/sequenceBuilder
Author: DoraSz
Author-email: szuucs.dora@gmail.com
License: UNKNOWN
Platform: UNKNOWN
Classifier: Programming Language :: Python :: 3
Classifier: License :: OSI Approved :: MIT License
Classifier: Operating System :: OS Independent
Requires-Dist: numpy
Requires-Dist: pandas
